igogo/__init__.py
igogo/context.py
igogo/core.py
igogo/exceptions.py
igogo/loaders.py
igogo/magic.py
igogo/output.py
igogo/yielder.py
igogo-1.1.0.dist-info/METADATA
igogo-1.1.0.dist-info/WHEEL
igogo-1.1.0.dist-info/licenses/LICENSE
igogo-1.1.0.dist-info/RECORD
