Metadata-Version: 2.1
Name: igogo
Version: 1.1.0
Summary: Execute several jupyter cells simultaneously
Project-URL: Homepage, https://github.com/alexdremov/igogo
Author-email: Alex Dremov <igogo@alexdremov.me>
License-Expression: MIT
License-File: LICENSE
Keywords: execute,ipython,jupyter,jupyterlab,python
Classifier: License :: OSI Approved :: MIT License
Classifier: Operating System :: OS Independent
Classifier: Programming Language :: Python :: 3
Requires-Python: >=3.8
Requires-Dist: greenback>=1.1.1
Requires-Dist: ipython>=8.0.0
Requires-Dist: matplotlib>=3.5.0
